{
  "Colors": {
    "Neutral": {
      "Neutral Alpha.8": { "value": "rgba(0, 0, 0, 0.8)" },
      "Neutral.12": { "value": "#f5f5f5" },
      "Neutral.1": { "value": "#e0e0e0" },
      "Neutral.2": { "value": "#d0d0d0" },
      "Neutral Alpha.1": { "value": "rgba(0, 0, 0, 0.1)" },
      "Neutral Alpha.2": { "value": "rgba(0, 0, 0, 0.2)" },
      "Neutral Alpha.3": { "value": "rgba(0, 0, 0, 0.3)" },
      "Neutral Alpha.4": { "value": "rgba(0, 0, 0, 0.4)" }
    },
    "Indigo": {
      "Alpha.1": { "value": "rgba(38, 57, 77, 0.1)" },
      "Alpha.2": { "value": "rgba(38, 57, 77, 0.2)" },
      "Alpha.3": { "value": "rgba(38, 57, 77, 0.3)" },
      "Alpha.4": { "value": "rgba(38, 57, 77, 0.4)" },
      "Alpha.5": { "value": "rgba(38, 57, 77, 0.5)" },
      "Alpha.6": { "value": "rgba(38, 57, 77, 0.6)" },
      "Alpha.7": { "value": "rgba(38, 57, 77, 0.7)" },
      "Alpha.8": { "value": "rgba(38, 57, 77, 0.8)" },
      "Alpha.9": { "value": "rgba(38, 57, 77, 0.9)" },
      "Alpha.10": { "value": "rgba(38, 57, 77, 1)" },
      "Alpha.11": { "value": "rgba(38, 57, 77, 0.7)" },
      "Alpha.12": { "value": "rgba(38, 57, 77, 0.5)" },
      "1": { "value": "#3b82f6" },
      "2": { "value": "#2563eb" },
      "3": { "value": "#1d4ed8" },
      "4": { "value": "#1e40af" },
      "5": { "value": "#1e3a8a" },
      "6": { "value": "#1e2a6e" },
      "7": { "value": "#172e8d" },
      "8": { "value": "#0e2766" },
      "9": { "value": "#0c1c46" },
      "10": { "value": "#0a1831" },
      "11": { "value": "#0a1531" },
      "12": { "value": "#080f23" }
    },
    "Default": {
      "white": { "value": "#ffffff" }
    }
  },
  "Color scheme": {
    "Light": {
      "Variables": {
        "Misc": {
          "backdrop": { "value": "Colors.Neutral.Neutral Alpha.8" },
          "dark-to-white": { "value": "Colors.Neutral.Neutral.12" }
        },
        "Effects": {
          "solid": { "value": "Colors.Default.white" }
        }
      }
    },
    "Dark": {
      "Variables": {
        "Misc": {
          "white-to-dark": { "value": "Colors.Neutral.Neutral.1" },
          "dark-to-white": { "value": "Colors.Default.white" }
        },
        "Effects": {
          "solid": { "value": "Colors.Neutral.Neutral.2" }
        }
      }
    }
  },
  "Theme": {
    "Theme A": {
      "Colors": {
        "Accent": {
          "Accent Alpha.1": { "value": "Colors.Indigo Alpha.1" },
          "Accent Alpha.2": { "value": "Colors.Indigo Alpha.2" },
          "Accent Alpha.3": { "value": "Colors.Indigo Alpha.3" },
          "Accent Alpha.4": { "value": "Colors.Indigo Alpha.4" },
          "Accent Alpha.5": { "value": "Colors.Indigo Alpha.5" },
          "Accent Alpha.6": { "value": "Colors.Indigo Alpha.6" },
          "Accent Alpha.7": { "value": "Colors.Indigo Alpha.7" },
          "Accent Alpha.8": { "value": "Colors.Indigo Alpha.8" },
          "Accent Alpha.9": { "value": "Colors.Indigo Alpha.9" },
          "Accent Alpha.10": { "value": "Colors.Indigo Alpha.10" },
          "Accent Alpha.11": { "value": "Colors.Indigo Alpha.11" },
          "Accent Alpha.12": { "value": "Colors.Indigo Alpha.12" },
          "1": { "value": "Colors.Indigo.1" },
          "2": { "value": "Colors.Indigo.2" },
          "3": { "value": "Colors.Indigo.3" },
          "4": { "value": "Colors.Indigo.4" },
          "5": { "value": "Colors.Indigo.5" },
          "6": { "value": "Colors.Indigo.6" },
          "7": { "value": "Colors.Indigo.7" },
          "8": { "value": "Colors.Indigo.8" },
          "9": { "value": "Colors.Indigo.9" },
          "10": { "value": "Colors.Indigo.10" },
          "11": { "value": "Colors.Indigo.11" },
          "12": { "value": "Colors.Indigo.12" }
        },
        "Neutral": {
          "Neutral Alpha.1": { "value": "Colors.Slate Alpha.1" },
          "Neutral Alpha.2": { "value": "Colors.Slate Alpha.2" },
          "Neutral Alpha.3": { "value": "Colors.Slate Alpha.3" },
          "Neutral Alpha.4": { "value": "Colors.Slate Alpha.4" },
          "Neutral Alpha.5": { "value": "Colors.Slate Alpha.5" },
          "Neutral Alpha.6": { "value": "Colors.Slate Alpha.6" },
          "Neutral Alpha.7": { "value": "Colors.Slate Alpha.7" },
          "Neutral Alpha.8": { "value": "Colors.Slate Alpha.8" },
          "Neutral Alpha.9": { "value": "Colors.Slate Alpha.9" },
          "Neutral Alpha.10": { "value": "Colors.Slate Alpha.10" },
          "Neutral Alpha.11": { "value": "Colors.Slate Alpha.11" },
          "Neutral Alpha.12": { "value": "Colors.Slate Alpha.12" }
        }
      }
    }
  }
}
